pyams/__init__.py
pyams/lib/__init__.py
pyams/lib/cad.py
pyams/lib/cpyams.py
pyams/lib/digital.py
pyams/lib/dynamic.py
pyams/lib/electrical.py
pyams/lib/options.py
pyams/lib/progressbar.py
pyams/lib/std.py
pyams/lib/unewton.py
pyams/lib/unewton_numpy.py
pyams/lib/utils.py
pyams/lib/__pycache__/__init__.cpython-313.pyc
pyams/lib/__pycache__/__init__.pypy311.pyc
pyams/lib/__pycache__/cad.cpython-313.pyc
pyams/lib/__pycache__/cad.pypy311.pyc
pyams/lib/__pycache__/cpyams.cpython-313.pyc
pyams/lib/__pycache__/cpyams.pypy311.pyc
pyams/lib/__pycache__/digital.cpython-313.pyc
pyams/lib/__pycache__/digital.pypy311.pyc
pyams/lib/__pycache__/dynamic.cpython-313.pyc
pyams/lib/__pycache__/dynamic.pypy311.pyc
pyams/lib/__pycache__/electrical.cpython-313.pyc
pyams/lib/__pycache__/electrical.pypy311.pyc
pyams/lib/__pycache__/options.cpython-313.pyc
pyams/lib/__pycache__/options.pypy311.pyc
pyams/lib/__pycache__/progressbar.cpython-313.pyc
pyams/lib/__pycache__/progressbar.pypy311.pyc
pyams/lib/__pycache__/std.cpython-313.pyc
pyams/lib/__pycache__/std.pypy311.pyc
pyams/lib/__pycache__/unewton.cpython-313.pyc
pyams/lib/__pycache__/unewton.pypy311.pyc
pyams/lib/__pycache__/unewton_numpy.cpython-313.pyc
pyams/lib/__pycache__/utils.cpython-313.pyc
pyams/lib/__pycache__/utils.pypy311.pyc
pyams/lib/temp/unewtonrgrgr.py
pyams/lib/temp/unewtonzzz.py
pyams/models/__init__.py
pyams/models/data.json
pyams/models/Analog/Basic/CCCS.py
pyams/models/Analog/Basic/CCVS.py
pyams/models/Analog/Basic/Capacitor.py
pyams/models/Analog/Basic/CapacitorIc.py
pyams/models/Analog/Basic/Conductor.py
pyams/models/Analog/Basic/Inductor.py
pyams/models/Analog/Basic/InductorIc.py
pyams/models/Analog/Basic/Load.py
pyams/models/Analog/Basic/NegativeResistance.py
pyams/models/Analog/Basic/NonlinearResistance.py
pyams/models/Analog/Basic/Resistor.py
pyams/models/Analog/Basic/Switch.py
pyams/models/Analog/Basic/SwitchC.py
pyams/models/Analog/Basic/SwitchSample.py
pyams/models/Analog/Basic/Transformer.py
pyams_lib-0.2.4.dist-info/licenses/LICENSE
pyams_lib-0.2.4.dist-info/METADATA
pyams_lib-0.2.4.dist-info/WHEEL
pyams_lib-0.2.4.dist-info/top_level.txt
pyams_lib-0.2.4.dist-info/RECORD
