Metadata-Version: 2.4
Name: pyams_lib
Version: 0.2.4
Summary: Simulation modeling of analog, digital and mixed-signal electronic elements and circuits
Home-page: https://github.com/d-fathi/pyams_lib
Author: Dhiabi.Fathi
Author-email: dhiabi.fathi@gmail.com
Project-URL: Website, https://pyams-lib.readthedocs.io/
Project-URL: Source, https://github.com/d-fathi/pyams_lib
Project-URL: Documentation, https://pyams-lib.readthedocs.io/
Project-URL: Bug Tracker, https://github.com/d-fathi/pyams_lib/issues
Project-URL: Support, https://github.com/d-fathi/pyams_lib/discussions
Project-URL: Donate, https://ko-fi.com/pyams
Keywords: simulation,circuit,electronics,mixed-signal,analog,EDA,electronic modeling,electrical engineering
Classifier: Development Status :: 4 - Beta
Classifier: Intended Audience :: Science/Research
Classifier: Intended Audience :: Developers
Classifier: Topic :: Scientific/Engineering :: Electronic Design Automation (EDA)
Classifier: License :: OSI Approved :: GNU General Public License v3 (GPLv3)
Classifier: Programming Language :: Python :: 3
Classifier: Operating System :: OS Independent
Requires-Python: >=3.6
License-File: LICENSE
Dynamic: author
Dynamic: author-email
Dynamic: classifier
Dynamic: description
Dynamic: description-content-type
Dynamic: home-page
Dynamic: keywords
Dynamic: license-file
Dynamic: project-url
Dynamic: requires-python
Dynamic: summary
